{
  "version": "https://jsonfeed.org/version/1",
  "icon": "https://www.trackawesomelist.com/icon.png",
  "favicon": "https://www.trackawesomelist.com/favicon.ico",
  "language": "en",
  "title": "Track Awesome Open Hardware Updates Weekly",
  "_seo_title": "Track Awesome Open Hardware (delftopenhardware/awesome-open-hardware) Updates Weekly - Track Awesome List",
  "_site_title": "Track Awesome List",
  "description": "🛠Helpful items for making open source hardware projects.",
  "home_page_url": "https://www.trackawesomelist.com/delftopenhardware/awesome-open-hardware/week/",
  "feed_url": "https://www.trackawesomelist.com/delftopenhardware/awesome-open-hardware/week/feed.json",
  "items": [
    {
      "id": "https://www.trackawesomelist.com/2024/3/",
      "title": "Awesome Open Hardware Updates on Jan 15 - Jan 21, 2024",
      "_short_title": "Jan 15 - Jan 21, 2024",
      "_slug": "2024/3/",
      "summary": "1 awesome projects updated on Jan 15 - Jan 21, 2024",
      "_filepath": "/content/2024/3/README.md",
      "url": "https://www.trackawesomelist.com/2024/3/",
      "date_published": "2024-01-17T08:57:41.000Z",
      "date_modified": "2024-01-17T08:57:41.000Z",
      "content_text": "\n\n### Talks\n\n*   [On behalf of mankind: thank you for sharing!](https://www.youtube.com/watch?v=HBS8sS138GE) - TEDx talk by Jerry de Vos",
      "content_html": "<h3><p>Talks</p>\n</h3>\n<ul>\n<li><a href=\"https://www.youtube.com/watch?v=HBS8sS138GE\" rel=\"noopener noreferrer\">On behalf of mankind: thank you for sharing!</a> - TEDx talk by Jerry de Vos</li>\n</ul>\n"
    },
    {
      "id": "https://www.trackawesomelist.com/2023/48/",
      "title": "Awesome Open Hardware Updates on Nov 27 - Dec 03, 2023",
      "_short_title": "Nov 27 - Dec 03, 2023",
      "_slug": "2023/48/",
      "summary": "1 awesome projects updated on Nov 27 - Dec 03, 2023",
      "_filepath": "/content/2023/48/README.md",
      "url": "https://www.trackawesomelist.com/2023/48/",
      "date_published": "2023-12-01T20:28:06.000Z",
      "date_modified": "2023-12-01T20:28:06.000Z",
      "content_text": "\n\n### Projects\n\n*   [Mekanika](https://www.mekanika.io/) - Tools & Machines for Makers",
      "content_html": "<h3><p>Projects</p>\n</h3>\n<ul>\n<li><a href=\"https://www.mekanika.io/\" rel=\"noopener noreferrer\">Mekanika</a> - Tools &amp; Machines for Makers</li>\n</ul>\n"
    },
    {
      "id": "https://www.trackawesomelist.com/2023/38/",
      "title": "Awesome Open Hardware Updates on Sep 18 - Sep 24, 2023",
      "_short_title": "Sep 18 - Sep 24, 2023",
      "_slug": "2023/38/",
      "summary": "1 awesome projects updated on Sep 18 - Sep 24, 2023",
      "_filepath": "/content/2023/38/README.md",
      "url": "https://www.trackawesomelist.com/2023/38/",
      "date_published": "2023-09-21T11:36:28.000Z",
      "date_modified": "2023-09-21T11:36:28.000Z",
      "content_text": "\n\n### Projects\n\n*   [PiKVM](https://pikvm.org/) - Open and inexpensive DIY IP-KVM based on Raspberry Pi.",
      "content_html": "<h3><p>Projects</p>\n</h3>\n<ul>\n<li><a href=\"https://pikvm.org/\" rel=\"noopener noreferrer\">PiKVM</a> - Open and inexpensive DIY IP-KVM based on Raspberry Pi.</li>\n</ul>\n"
    },
    {
      "id": "https://www.trackawesomelist.com/2023/30/",
      "title": "Awesome Open Hardware Updates on Jul 24 - Jul 30, 2023",
      "_short_title": "Jul 24 - Jul 30, 2023",
      "_slug": "2023/30/",
      "summary": "3 awesome projects updated on Jul 24 - Jul 30, 2023",
      "_filepath": "/content/2023/30/README.md",
      "url": "https://www.trackawesomelist.com/2023/30/",
      "date_published": "2023-07-28T10:39:29.000Z",
      "date_modified": "2023-07-28T10:39:29.000Z",
      "content_text": "\n\n### Projects\n\n*   [Opulo](https://docs.opulo.io/) - Project that develops a pick and place machine.\n*   [FarmBot](https://farm.bot/pages/open-source) - automated gardening machine to grow vegetables.\n\n### Books\n\n*   [Free to Make](https://books.google.nl/books?id=jz1bCwAAQBAJ\\&lpg=PA93\\&dq=open%20source%20hardware\\&pg=PP1##v=onepage\\&q=open%20source%20hardware\\&f=false) -  Book by Dale Dougherty, how the maker movement is changing our schools, our jobs, and our minds.",
      "content_html": "<h3><p>Projects</p>\n</h3>\n<ul>\n<li><a href=\"https://docs.opulo.io/\" rel=\"noopener noreferrer\">Opulo</a> - Project that develops a pick and place machine.</li>\n</ul>\n\n<ul>\n<li><a href=\"https://farm.bot/pages/open-source\" rel=\"noopener noreferrer\">FarmBot</a> - automated gardening machine to grow vegetables.</li>\n</ul>\n<h3><p>Books</p>\n</h3>\n<ul>\n<li><a href=\"https://books.google.nl/books?id=jz1bCwAAQBAJ&amp;lpg=PA93&amp;dq=open%20source%20hardware&amp;pg=PP1##v=onepage&amp;q=open%20source%20hardware&amp;f=false\" rel=\"noopener noreferrer\">Free to Make</a> -  Book by Dale Dougherty, how the maker movement is changing our schools, our jobs, and our minds.</li>\n</ul>\n"
    },
    {
      "id": "https://www.trackawesomelist.com/2022/47/",
      "title": "Awesome Open Hardware Updates on Nov 21 - Nov 27, 2022",
      "_short_title": "Nov 21 - Nov 27, 2022",
      "_slug": "2022/47/",
      "summary": "1 awesome projects updated on Nov 21 - Nov 27, 2022",
      "_filepath": "/content/2022/47/README.md",
      "url": "https://www.trackawesomelist.com/2022/47/",
      "date_published": "2022-11-23T12:19:56.000Z",
      "date_modified": "2022-11-23T12:19:56.000Z",
      "content_text": "\n\n### Projects\n\n*   [Open Gamma Detector (⭐303)](https://github.com/Open-Gamma-Project/Open-Gamma-Detector) - Hackable, low-cost gamma-ray spectrometer.",
      "content_html": "<h3><p>Projects</p>\n</h3>\n<ul>\n<li><a href=\"https://github.com/Open-Gamma-Project/Open-Gamma-Detector\" rel=\"noopener noreferrer\">Open Gamma Detector (⭐303)</a> - Hackable, low-cost gamma-ray spectrometer.</li>\n</ul>\n"
    },
    {
      "id": "https://www.trackawesomelist.com/2022/43/",
      "title": "Awesome Open Hardware Updates on Oct 24 - Oct 30, 2022",
      "_short_title": "Oct 24 - Oct 30, 2022",
      "_slug": "2022/43/",
      "summary": "1 awesome projects updated on Oct 24 - Oct 30, 2022",
      "_filepath": "/content/2022/43/README.md",
      "url": "https://www.trackawesomelist.com/2022/43/",
      "date_published": "2022-10-24T03:55:39.000Z",
      "date_modified": "2022-10-24T03:55:39.000Z",
      "content_text": "\n\n### Projects\n\n*   [Open-Source-Rover (⭐8.8k)](https://github.com/nasa-jpl/open-source-rover) - A six wheeled, build-it-yourself, open-source rover.",
      "content_html": "<h3><p>Projects</p>\n</h3>\n<ul>\n<li><a href=\"https://github.com/nasa-jpl/open-source-rover\" rel=\"noopener noreferrer\">Open-Source-Rover (⭐8.8k)</a> - A six wheeled, build-it-yourself, open-source rover.</li>\n</ul>\n"
    },
    {
      "id": "https://www.trackawesomelist.com/2022/31/",
      "title": "Awesome Open Hardware Updates on Aug 01 - Aug 07, 2022",
      "_short_title": "Aug 01 - Aug 07, 2022",
      "_slug": "2022/31/",
      "summary": "1 awesome projects updated on Aug 01 - Aug 07, 2022",
      "_filepath": "/content/2022/31/README.md",
      "url": "https://www.trackawesomelist.com/2022/31/",
      "date_published": "2022-08-07T09:36:09.000Z",
      "date_modified": "2022-08-07T09:36:09.000Z",
      "content_text": "\n\n### Projects\n\n*   [RepRap](https://reprap.org/wiki/RepRap) - Humanity's first general-purpose, self-replicating manufacturing machine.",
      "content_html": "<h3><p>Projects</p>\n</h3>\n<ul>\n<li><a href=\"https://reprap.org/wiki/RepRap\" rel=\"noopener noreferrer\">RepRap</a> - Humanity's first general-purpose, self-replicating manufacturing machine.</li>\n</ul>\n"
    },
    {
      "id": "https://www.trackawesomelist.com/2022/26/",
      "title": "Awesome Open Hardware Updates on Jun 27 - Jul 03, 2022",
      "_short_title": "Jun 27 - Jul 03, 2022",
      "_slug": "2022/26/",
      "summary": "3 awesome projects updated on Jun 27 - Jul 03, 2022",
      "_filepath": "/content/2022/26/README.md",
      "url": "https://www.trackawesomelist.com/2022/26/",
      "date_published": "2022-06-27T10:34:11.000Z",
      "date_modified": "2022-06-27T21:16:02.000Z",
      "content_text": "\n\n### Projects\n\n*   [Mutable Instruments](https://mutable-instruments.net/) - Open-source eurorack classics.\n*   [Winterbloom](https://winterbloom.com) - Open-source eurorack modules, Thea has some stellar design write-ups on her blog.\n\n### Related awesome\n\n*   [Awesome Electronics (⭐6.6k)](https://github.com/kitspace/awesome-electronics) - A curated list of awesome resources for electronic engineers and hobbyists.",
      "content_html": "<h3><p>Projects</p>\n</h3>\n<ul>\n<li><a href=\"https://mutable-instruments.net/\" rel=\"noopener noreferrer\">Mutable Instruments</a> - Open-source eurorack classics.</li>\n</ul>\n\n<ul>\n<li><a href=\"https://winterbloom.com\" rel=\"noopener noreferrer\">Winterbloom</a> - Open-source eurorack modules, Thea has some stellar design write-ups on her blog.</li>\n</ul>\n<h3><p>Related awesome</p>\n</h3>\n<ul>\n<li><a href=\"https://github.com/kitspace/awesome-electronics\" rel=\"noopener noreferrer\">Awesome Electronics (⭐6.6k)</a> - A curated list of awesome resources for electronic engineers and hobbyists.</li>\n</ul>\n"
    },
    {
      "id": "https://www.trackawesomelist.com/2022/25/",
      "title": "Awesome Open Hardware Updates on Jun 20 - Jun 26, 2022",
      "_short_title": "Jun 20 - Jun 26, 2022",
      "_slug": "2022/25/",
      "summary": "6 awesome projects updated on Jun 20 - Jun 26, 2022",
      "_filepath": "/content/2022/25/README.md",
      "url": "https://www.trackawesomelist.com/2022/25/",
      "date_published": "2022-06-23T11:21:19.000Z",
      "date_modified": "2022-06-23T14:31:33.000Z",
      "content_text": "\n\n### Talks\n\n*   [Get your open hardware manufactured](https://www.youtube.com/watch?v=ifTaGRTPwLc) - Tips by Ian of Dangerous Prototypes.\n\n### Papers\n\n*   [Haves and have nots must find a better way: The case for open scientific hardware](https://doi.org/10.1371/journal.pbio.3000014) - Paper by Andre Maia Chagas\n*   [Open Labware: 3-D Printing Your Own Lab Equipment](https://doi.org/10.1371/journal.pbio.1002086) - Paper by Tom Baden, Andre Maia Chagas, Greg Gage, Timothy Marzullo, Lucia L. Prieto-Godino, Thomas Euler\n\n### Platforms\n\n*   [Kitspace.org](https://kitspace.org) - A place to build and share electronics projects.\n\n### Training programs\n\n*   [Open Hardware Makers](https://openhardware.space)\n*   [Open Hardware Academy](https://openhardware.academy/)",
      "content_html": "<h3><p>Talks</p>\n</h3>\n<ul>\n<li><a href=\"https://www.youtube.com/watch?v=ifTaGRTPwLc\" rel=\"noopener noreferrer\">Get your open hardware manufactured</a> - Tips by Ian of Dangerous Prototypes.</li>\n</ul>\n<h3><p>Papers</p>\n</h3>\n<ul>\n<li><a href=\"https://doi.org/10.1371/journal.pbio.3000014\" rel=\"noopener noreferrer\">Haves and have nots must find a better way: The case for open scientific hardware</a> - Paper by Andre Maia Chagas</li>\n</ul>\n\n<ul>\n<li><a href=\"https://doi.org/10.1371/journal.pbio.1002086\" rel=\"noopener noreferrer\">Open Labware: 3-D Printing Your Own Lab Equipment</a> - Paper by Tom Baden, Andre Maia Chagas, Greg Gage, Timothy Marzullo, Lucia L. Prieto-Godino, Thomas Euler</li>\n</ul>\n<h3><p>Platforms</p>\n</h3>\n<ul>\n<li><a href=\"https://kitspace.org\" rel=\"noopener noreferrer\">Kitspace.org</a> - A place to build and share electronics projects.</li>\n</ul>\n<h3><p>Training programs</p>\n</h3>\n<ul>\n<li><a href=\"https://openhardware.space\" rel=\"noopener noreferrer\">Open Hardware Makers</a></li>\n</ul>\n\n<ul>\n<li><a href=\"https://openhardware.academy/\" rel=\"noopener noreferrer\">Open Hardware Academy</a></li>\n</ul>\n"
    },
    {
      "id": "https://www.trackawesomelist.com/2022/20/",
      "title": "Awesome Open Hardware Updates on May 16 - May 22, 2022",
      "_short_title": "May 16 - May 22, 2022",
      "_slug": "2022/20/",
      "summary": "1 awesome projects updated on May 16 - May 22, 2022",
      "_filepath": "/content/2022/20/README.md",
      "url": "https://www.trackawesomelist.com/2022/20/",
      "date_published": "2022-05-22T09:50:28.000Z",
      "date_modified": "2022-05-22T09:50:28.000Z",
      "content_text": "\n\n### Projects\n\n*   [OpenMV (⭐2.6k)](https://github.com/openmv/openmv) - Open-source, low-cost machine vision platform.",
      "content_html": "<h3><p>Projects</p>\n</h3>\n<ul>\n<li><a href=\"https://github.com/openmv/openmv\" rel=\"noopener noreferrer\">OpenMV (⭐2.6k)</a> - Open-source, low-cost machine vision platform.</li>\n</ul>\n"
    },
    {
      "id": "https://www.trackawesomelist.com/2022/4/",
      "title": "Awesome Open Hardware Updates on Jan 24 - Jan 30, 2022",
      "_short_title": "Jan 24 - Jan 30, 2022",
      "_slug": "2022/4/",
      "summary": "10 awesome projects updated on Jan 24 - Jan 30, 2022",
      "_filepath": "/content/2022/4/README.md",
      "url": "https://www.trackawesomelist.com/2022/4/",
      "date_published": "2022-01-28T15:53:28.000Z",
      "date_modified": "2022-01-28T16:12:53.000Z",
      "content_text": "\n\n### Projects\n\n*   [Precious Plastic](https://www.preciousplastic.com/) - Tools to make plastic recycling as simple as possible.\n\n### Papers\n\n*   [What is the “Source” of Open Source Hardware?](https://doi.org/10.5334/joh.7) - Paper by Jérémy Bonvoisin, Robert Mies, Jean-François Boujut, Rainer Stark.\n*   [Towards national policy for open source hardware research: The case of Finland](https://doi.org/10.1016/j.techfore.2020.119986) - Paper by I. T. S. Heikkinen, H. Savin, J. Partanen, J. SeppäläJ, M. Pearce.\n*   [Open-Source Hardware in Education: A Systematic Mapping Study](http://dx.doi.org/10.1109/ACCESS.2018.2881929) - Paper by Ruben Heradio, Jesus Chacon, Hector Vargas, Daniel Galan, Jacobo Saenz, Luis De La Torre, Sebastian Dormido.\n\n### Podcasts\n\n*   [Amp hour](https://podcasts.google.com/feed/aHR0cHM6Ly90aGVhbXBob3VyLmxpYnN5bi5jb20vcnNz/episode/aHR0cDovL3d3dy50aGVhbXBob3VyLmNvbS8_cD0xNTg?sa=X\\&ved=0CAIQuIEEahcKEwjgkZnWjPr0AhUAAAAAHQAAAAAQCA) - Open Hardware and The Creative Economy.\n*   [Semiconductor Insiders](https://semiwiki.com/podcast/podcast-ep44-open-hardware-diversity-alliance/) - Open Hardware Diversity Alliance.\n*   [Open source hardware podcast](https://podcasts.google.com/feed/aHR0cHM6Ly9wcm9ncmFtbWluZ2VsZWN0cm9uaWNzLmNvbS9jYXRlZ29yeS9yYWRpby1zaG93L2ZlZWQv) - By the Programming Electronics Academy.\n\n### Further Readings\n\n*   [Open Source Guide](https://opensource.guide/) - A website created by GitHub to help people work on open source projects.\n*   [Open Collective](https://opencollective.com/) - Enables groups to quickly set up a collective, raise funds and manage them transparently.\n*   [OSHWA Certification](https://certification.oshwa.org/) -  Provides an easy and straightforward way for producers to indicate that their products meet a uniform and well-defined standard for open-source compliance.",
      "content_html": "<h3><p>Projects</p>\n</h3>\n<ul>\n<li><a href=\"https://www.preciousplastic.com/\" rel=\"noopener noreferrer\">Precious Plastic</a> - Tools to make plastic recycling as simple as possible.</li>\n</ul>\n<h3><p>Papers</p>\n</h3>\n<ul>\n<li><a href=\"https://doi.org/10.5334/joh.7\" rel=\"noopener noreferrer\">What is the “Source” of Open Source Hardware?</a> - Paper by Jérémy Bonvoisin, Robert Mies, Jean-François Boujut, Rainer Stark.</li>\n</ul>\n\n<ul>\n<li><a href=\"https://doi.org/10.1016/j.techfore.2020.119986\" rel=\"noopener noreferrer\">Towards national policy for open source hardware research: The case of Finland</a> - Paper by I. T. S. Heikkinen, H. Savin, J. Partanen, J. SeppäläJ, M. Pearce.</li>\n</ul>\n\n<ul>\n<li><a href=\"http://dx.doi.org/10.1109/ACCESS.2018.2881929\" rel=\"noopener noreferrer\">Open-Source Hardware in Education: A Systematic Mapping Study</a> - Paper by Ruben Heradio, Jesus Chacon, Hector Vargas, Daniel Galan, Jacobo Saenz, Luis De La Torre, Sebastian Dormido.</li>\n</ul>\n<h3><p>Podcasts</p>\n</h3>\n<ul>\n<li><a href=\"https://podcasts.google.com/feed/aHR0cHM6Ly90aGVhbXBob3VyLmxpYnN5bi5jb20vcnNz/episode/aHR0cDovL3d3dy50aGVhbXBob3VyLmNvbS8_cD0xNTg?sa=X&amp;ved=0CAIQuIEEahcKEwjgkZnWjPr0AhUAAAAAHQAAAAAQCA\" rel=\"noopener noreferrer\">Amp hour</a> - Open Hardware and The Creative Economy.</li>\n</ul>\n\n<ul>\n<li><a href=\"https://semiwiki.com/podcast/podcast-ep44-open-hardware-diversity-alliance/\" rel=\"noopener noreferrer\">Semiconductor Insiders</a> - Open Hardware Diversity Alliance.</li>\n</ul>\n\n<ul>\n<li><a href=\"https://podcasts.google.com/feed/aHR0cHM6Ly9wcm9ncmFtbWluZ2VsZWN0cm9uaWNzLmNvbS9jYXRlZ29yeS9yYWRpby1zaG93L2ZlZWQv\" rel=\"noopener noreferrer\">Open source hardware podcast</a> - By the Programming Electronics Academy.</li>\n</ul>\n<h3><p>Further Readings</p>\n</h3>\n<ul>\n<li><a href=\"https://opensource.guide/\" rel=\"noopener noreferrer\">Open Source Guide</a> - A website created by GitHub to help people work on open source projects.</li>\n</ul>\n\n<ul>\n<li><a href=\"https://opencollective.com/\" rel=\"noopener noreferrer\">Open Collective</a> - Enables groups to quickly set up a collective, raise funds and manage them transparently.</li>\n</ul>\n\n<ul>\n<li><a href=\"https://certification.oshwa.org/\" rel=\"noopener noreferrer\">OSHWA Certification</a> -  Provides an easy and straightforward way for producers to indicate that their products meet a uniform and well-defined standard for open-source compliance.</li>\n</ul>\n"
    },
    {
      "id": "https://www.trackawesomelist.com/2022/2/",
      "title": "Awesome Open Hardware Updates on Jan 10 - Jan 16, 2022",
      "_short_title": "Jan 10 - Jan 16, 2022",
      "_slug": "2022/2/",
      "summary": "9 awesome projects updated on Jan 10 - Jan 16, 2022",
      "_filepath": "/content/2022/2/README.md",
      "url": "https://www.trackawesomelist.com/2022/2/",
      "date_published": "2022-01-13T10:05:14.000Z",
      "date_modified": "2022-01-13T20:57:48.000Z",
      "content_text": "\n\n### Projects\n\n*   [Biohack Academy](http://biohackacademy.github.io/) - Open-source biotechnological hardware such as Incubator, Thermocycler, Centrifuge, Microscope, etc.\n*   [GaudiLab](http://www.gaudi.ch/GaudiLabs/?page_id=19) - Open-source hardware projects for biology laboratories.\n\n### Platforms\n\n*   [Instructables](http://www.instructables.com/tag/type-id/category-technology/) - Instructables is a place that lets you explore, document, and share your creations.\n*   [Hackaday.io](https://hackaday.io/) - Hackaday.io is the world's largest collaborative hardware development community.\n*   [Openlifescience](https://openlifesci.org/) - Program to make Open Science ambassadors in research.\n*   [Thingiverse](https://www.thingiverse.com/) - A platform for sharing and contributing to design hardware for 3D printing, laser cutting and CNC milling.\n\n### Further Readings\n\n*   [Wikipedia](https://en.wikipedia.org/wiki/Open-source_hardware) - General information about Open Source Hardware.\n*   [The Journal of Open Hardware](https://openhardware.metajnl.com/) - (JOH) is a peer reviewed open access publication for open hardware research and development.\n*   [HardwareX Journal](https://www.journals.elsevier.com/hardwarex) - An open access scientific hardware journal.",
      "content_html": "<h3><p>Projects</p>\n</h3>\n<ul>\n<li><a href=\"http://biohackacademy.github.io/\" rel=\"noopener noreferrer\">Biohack Academy</a> - Open-source biotechnological hardware such as Incubator, Thermocycler, Centrifuge, Microscope, etc.</li>\n</ul>\n\n<ul>\n<li><a href=\"http://www.gaudi.ch/GaudiLabs/?page_id=19\" rel=\"noopener noreferrer\">GaudiLab</a> - Open-source hardware projects for biology laboratories.</li>\n</ul>\n<h3><p>Platforms</p>\n</h3>\n<ul>\n<li><a href=\"http://www.instructables.com/tag/type-id/category-technology/\" rel=\"noopener noreferrer\">Instructables</a> - Instructables is a place that lets you explore, document, and share your creations.</li>\n</ul>\n\n<ul>\n<li><a href=\"https://hackaday.io/\" rel=\"noopener noreferrer\">Hackaday.io</a> - Hackaday.io is the world's largest collaborative hardware development community.</li>\n</ul>\n\n<ul>\n<li><a href=\"https://openlifesci.org/\" rel=\"noopener noreferrer\">Openlifescience</a> - Program to make Open Science ambassadors in research.</li>\n</ul>\n\n<ul>\n<li><a href=\"https://www.thingiverse.com/\" rel=\"noopener noreferrer\">Thingiverse</a> - A platform for sharing and contributing to design hardware for 3D printing, laser cutting and CNC milling.</li>\n</ul>\n<h3><p>Further Readings</p>\n</h3>\n<ul>\n<li><a href=\"https://en.wikipedia.org/wiki/Open-source_hardware\" rel=\"noopener noreferrer\">Wikipedia</a> - General information about Open Source Hardware.</li>\n</ul>\n\n<ul>\n<li><a href=\"https://openhardware.metajnl.com/\" rel=\"noopener noreferrer\">The Journal of Open Hardware</a> - (JOH) is a peer reviewed open access publication for open hardware research and development.</li>\n</ul>\n\n<ul>\n<li><a href=\"https://www.journals.elsevier.com/hardwarex\" rel=\"noopener noreferrer\">HardwareX Journal</a> - An open access scientific hardware journal.</li>\n</ul>\n"
    },
    {
      "id": "https://www.trackawesomelist.com/2022/1/",
      "title": "Awesome Open Hardware Updates on Jan 03 - Jan 09, 2022",
      "_short_title": "Jan 03 - Jan 09, 2022",
      "_slug": "2022/1/",
      "summary": "35 awesome projects updated on Jan 03 - Jan 09, 2022",
      "_filepath": "/content/2022/1/README.md",
      "url": "https://www.trackawesomelist.com/2022/1/",
      "date_published": "2022-01-07T10:24:35.000Z",
      "date_modified": "2022-01-07T10:24:35.000Z",
      "content_text": "\n\n### Projects\n\n*   [Arduino](https://www.arduino.cc/) - Arduino is an open-source electronics platform.\n*   [Prusa3D](https://www.prusa3d.com/) - 3D printer manufacturer who shares their work open online.\n*   [Open Source Ecology](https://www.opensourceecology.org/) - Industrial machines made open.\n*   [SafeCast](https://safecast.org/) - Environmental measurements for the public domain.\n*   [WikiHouse](https://www.wikihouse.cc/) - Digital designed open housing.\n*   [OpenBCI](https://openbci.com/) - Brain computer interface.\n*   [OpenSPIM](https://openspim.org/) - Open Access platform for Three-dimensional (3D) microscopy.\n*   [mesoSPIM](http://mesospim.org/) - Open-source light-sheet microscopes for imaging in cleared tissue.\n*   [openUC2 (⭐497)](https://github.com/openUC2/UC2-GIT) - Open-source modular microscopy toolbox.\n*   [OpenFlexure](https://openflexure.org/) - Open-source, 3D-printed microscope, including a precise mechanical stage.\n\n### Talks\n\n*   [How Open Hardware will Take Over the World](https://www.youtube.com/watch?v=Rfu_MKgu2Ik) - TEDx talk by Nathan Seidle.\n*   [Revolution of the open hardware](https://www.youtube.com/watch?v=t56bojFAnUg) - TEDx talk by Bram Geenen.\n*   [Why do open hardware](https://www.youtube.com/watch?v=UYRhupdnUcY) - Talk by Limor Fried (ladyada).\n*   [Open Hardware Projects to Fight COVID-19](https://www.youtube.com/watch?v=c1pwbnDAub0) - Collection video from N-O-D-E.\n*   [Designing Open Hardware for 21st century science](https://www.youtube.com/watch?v=Od_9yJqc098) - Presentation by Andre Maia Chagas.\n*   [Why open source hardware is(n't) working](https://www.youtube.com/watch?v=7ifGu22bhd4) - Presentation by David Cuartielles.\n*   [Open source and the future of hardware](https://www.youtube.com/watch?v=_EZT57dtWHM) - Talk by Neil Gershenfeld.\n\n### Papers\n\n*   [Emerging Business Models for Open Source Hardware](https://papers.ssrn.com/sol3/papers.cfm?abstract_id=3331121) - Paper by Joshua M. Pearce.\n\n### Conferences\n\n*   [Fosdem](https://fosdem.org/2022/) - Open Source event online on 5 & 6 February 2022.\n*   [Open Hardware Summit](https://2022.oshwa.org/) - Annual conference on open hardware on 22 April 2022.\n*   [Maker Faire](https://makerfaire.com/) - A celebration of the Maker Movement, locally organized.\n\n### Platforms\n\n*   [Open Hardware Repository](https://ohwr.org/welcome) - For electronics designers at experimental physics facilities to collaborate on open hardware designs.\n*   [Open Hardware Observatory](https://en.oho.wiki/wiki/Home) - Free blueprints for sustainable open hardware.\n*   [Hackster.io](https://www.hackster.io/about) - Connecting developers where exploring tomorrow starts today.\n*   [Openhardware.io](https://www.openhardware.io/about) - Tracking amazing open hardware projects.\n*   [Openhardware.science](https://openhardware.science/) - Make open science hardware ubiquitous by 2025.\n\n### Podcasts\n\n*   [Road to Open Science](https://open.spotify.com/episode/46WwrOofygFyGrp6X42NOe?si=_qxPzPXkQaGNBqB-bnKwyw) - Episode on open hardware in the Netherlands.\n*   [Physics Worlds](https://open.spotify.com/episode/4pjaUpl96YhjqBvjzV0K1H?si=ssJJH7ouSOW_ttGvF2Mtdg) - Episode on the global impact of open hardware.\n*   [Command Line Heroes](https://open.spotify.com/episode/1yGuG9TKvS2lkH7wgRO8YF?si=PwAZCT0qSxW87HQlCa7AeA) -  Episode Makers unite.\n*   [A-podcast](https://open.spotify.com/episode/2Zp3q6ePDCp0Yeyq9ADDny?si=8_CuBG2ESEeoxvcspVi3Xg) -  Open source hardware is the future.\n\n### Books\n\n*   [Building open source hardware](https://books.google.nl/books?id=wg27BQAAQBAJ\\&lpg=PP1\\&dq=open%20source%20hardware\\&pg=PP1##v=onepage\\&q=open%20source%20hardware\\&f=false) - Book by Alicia Gibb, on building open source hardware from 2014.\n*   [Open-source Lab](https://books.google.nl/books?id=0bOKAAAAQBAJ\\&lpg=PP1\\&dq=open%20source%20hardware\\&pg=PP1##v=onepage\\&q=open%20source%20hardware\\&f=false) - Book by Josua m. Pearce, how to build your own hardware and reduce costs.\n*   [The bridge](https://www.nae.edu/174695/Fall-Bridge-on-Open-Source-Hardware) - Issue of the national academy of engineering on open source hardware.\n\n### Related awesome\n\n*   [Awesome Open Electronics (⭐605)](https://github.com/ajaymnk/open-electronics) - List with resources for Electronics Enthusiasts.\n*   [Awesome Open (⭐85)](https://github.com/paulhendricks/awesome-open) - A list of open companies and communities.",
      "content_html": "<h3><p>Projects</p>\n</h3>\n<ul>\n<li><a href=\"https://www.arduino.cc/\" rel=\"noopener noreferrer\">Arduino</a> - Arduino is an open-source electronics platform.</li>\n</ul>\n\n<ul>\n<li><a href=\"https://www.prusa3d.com/\" rel=\"noopener noreferrer\">Prusa3D</a> - 3D printer manufacturer who shares their work open online.</li>\n</ul>\n\n<ul>\n<li><a href=\"https://www.opensourceecology.org/\" rel=\"noopener noreferrer\">Open Source Ecology</a> - Industrial machines made open.</li>\n</ul>\n\n<ul>\n<li><a href=\"https://safecast.org/\" rel=\"noopener noreferrer\">SafeCast</a> - Environmental measurements for the public domain.</li>\n</ul>\n\n<ul>\n<li><a href=\"https://www.wikihouse.cc/\" rel=\"noopener noreferrer\">WikiHouse</a> - Digital designed open housing.</li>\n</ul>\n\n<ul>\n<li><a href=\"https://openbci.com/\" rel=\"noopener noreferrer\">OpenBCI</a> - Brain computer interface.</li>\n</ul>\n\n<ul>\n<li><a href=\"https://openspim.org/\" rel=\"noopener noreferrer\">OpenSPIM</a> - Open Access platform for Three-dimensional (3D) microscopy.</li>\n</ul>\n\n<ul>\n<li><a href=\"http://mesospim.org/\" rel=\"noopener noreferrer\">mesoSPIM</a> - Open-source light-sheet microscopes for imaging in cleared tissue.</li>\n</ul>\n\n<ul>\n<li><a href=\"https://github.com/openUC2/UC2-GIT\" rel=\"noopener noreferrer\">openUC2 (⭐497)</a> - Open-source modular microscopy toolbox.</li>\n</ul>\n\n<ul>\n<li><a href=\"https://openflexure.org/\" rel=\"noopener noreferrer\">OpenFlexure</a> - Open-source, 3D-printed microscope, including a precise mechanical stage.</li>\n</ul>\n<h3><p>Talks</p>\n</h3>\n<ul>\n<li><a href=\"https://www.youtube.com/watch?v=Rfu_MKgu2Ik\" rel=\"noopener noreferrer\">How Open Hardware will Take Over the World</a> - TEDx talk by Nathan Seidle.</li>\n</ul>\n\n<ul>\n<li><a href=\"https://www.youtube.com/watch?v=t56bojFAnUg\" rel=\"noopener noreferrer\">Revolution of the open hardware</a> - TEDx talk by Bram Geenen.</li>\n</ul>\n\n<ul>\n<li><a href=\"https://www.youtube.com/watch?v=UYRhupdnUcY\" rel=\"noopener noreferrer\">Why do open hardware</a> - Talk by Limor Fried (ladyada).</li>\n</ul>\n\n<ul>\n<li><a href=\"https://www.youtube.com/watch?v=c1pwbnDAub0\" rel=\"noopener noreferrer\">Open Hardware Projects to Fight COVID-19</a> - Collection video from N-O-D-E.</li>\n</ul>\n\n<ul>\n<li><a href=\"https://www.youtube.com/watch?v=Od_9yJqc098\" rel=\"noopener noreferrer\">Designing Open Hardware for 21st century science</a> - Presentation by Andre Maia Chagas.</li>\n</ul>\n\n<ul>\n<li><a href=\"https://www.youtube.com/watch?v=7ifGu22bhd4\" rel=\"noopener noreferrer\">Why open source hardware is(n't) working</a> - Presentation by David Cuartielles.</li>\n</ul>\n\n<ul>\n<li><a href=\"https://www.youtube.com/watch?v=_EZT57dtWHM\" rel=\"noopener noreferrer\">Open source and the future of hardware</a> - Talk by Neil Gershenfeld.</li>\n</ul>\n<h3><p>Papers</p>\n</h3>\n<ul>\n<li><a href=\"https://papers.ssrn.com/sol3/papers.cfm?abstract_id=3331121\" rel=\"noopener noreferrer\">Emerging Business Models for Open Source Hardware</a> - Paper by Joshua M. Pearce.</li>\n</ul>\n<h3><p>Conferences</p>\n</h3>\n<ul>\n<li><a href=\"https://fosdem.org/2022/\" rel=\"noopener noreferrer\">Fosdem</a> - Open Source event online on 5 &amp; 6 February 2022.</li>\n</ul>\n\n<ul>\n<li><a href=\"https://2022.oshwa.org/\" rel=\"noopener noreferrer\">Open Hardware Summit</a> - Annual conference on open hardware on 22 April 2022.</li>\n</ul>\n\n<ul>\n<li><a href=\"https://makerfaire.com/\" rel=\"noopener noreferrer\">Maker Faire</a> - A celebration of the Maker Movement, locally organized.</li>\n</ul>\n<h3><p>Platforms</p>\n</h3>\n<ul>\n<li><a href=\"https://ohwr.org/welcome\" rel=\"noopener noreferrer\">Open Hardware Repository</a> - For electronics designers at experimental physics facilities to collaborate on open hardware designs.</li>\n</ul>\n\n<ul>\n<li><a href=\"https://en.oho.wiki/wiki/Home\" rel=\"noopener noreferrer\">Open Hardware Observatory</a> - Free blueprints for sustainable open hardware.</li>\n</ul>\n\n<ul>\n<li><a href=\"https://www.hackster.io/about\" rel=\"noopener noreferrer\">Hackster.io</a> - Connecting developers where exploring tomorrow starts today.</li>\n</ul>\n\n<ul>\n<li><a href=\"https://www.openhardware.io/about\" rel=\"noopener noreferrer\">Openhardware.io</a> - Tracking amazing open hardware projects.</li>\n</ul>\n\n<ul>\n<li><a href=\"https://openhardware.science/\" rel=\"noopener noreferrer\">Openhardware.science</a> - Make open science hardware ubiquitous by 2025.</li>\n</ul>\n<h3><p>Podcasts</p>\n</h3>\n<ul>\n<li><a href=\"https://open.spotify.com/episode/46WwrOofygFyGrp6X42NOe?si=_qxPzPXkQaGNBqB-bnKwyw\" rel=\"noopener noreferrer\">Road to Open Science</a> - Episode on open hardware in the Netherlands.</li>\n</ul>\n\n<ul>\n<li><a href=\"https://open.spotify.com/episode/4pjaUpl96YhjqBvjzV0K1H?si=ssJJH7ouSOW_ttGvF2Mtdg\" rel=\"noopener noreferrer\">Physics Worlds</a> - Episode on the global impact of open hardware.</li>\n</ul>\n\n<ul>\n<li><a href=\"https://open.spotify.com/episode/1yGuG9TKvS2lkH7wgRO8YF?si=PwAZCT0qSxW87HQlCa7AeA\" rel=\"noopener noreferrer\">Command Line Heroes</a> -  Episode Makers unite.</li>\n</ul>\n\n<ul>\n<li><a href=\"https://open.spotify.com/episode/2Zp3q6ePDCp0Yeyq9ADDny?si=8_CuBG2ESEeoxvcspVi3Xg\" rel=\"noopener noreferrer\">A-podcast</a> -  Open source hardware is the future.</li>\n</ul>\n<h3><p>Books</p>\n</h3>\n<ul>\n<li><a href=\"https://books.google.nl/books?id=wg27BQAAQBAJ&amp;lpg=PP1&amp;dq=open%20source%20hardware&amp;pg=PP1##v=onepage&amp;q=open%20source%20hardware&amp;f=false\" rel=\"noopener noreferrer\">Building open source hardware</a> - Book by Alicia Gibb, on building open source hardware from 2014.</li>\n</ul>\n\n<ul>\n<li><a href=\"https://books.google.nl/books?id=0bOKAAAAQBAJ&amp;lpg=PP1&amp;dq=open%20source%20hardware&amp;pg=PP1##v=onepage&amp;q=open%20source%20hardware&amp;f=false\" rel=\"noopener noreferrer\">Open-source Lab</a> - Book by Josua m. Pearce, how to build your own hardware and reduce costs.</li>\n</ul>\n\n<ul>\n<li><a href=\"https://www.nae.edu/174695/Fall-Bridge-on-Open-Source-Hardware\" rel=\"noopener noreferrer\">The bridge</a> - Issue of the national academy of engineering on open source hardware.</li>\n</ul>\n<h3><p>Related awesome</p>\n</h3>\n<ul>\n<li><a href=\"https://github.com/ajaymnk/open-electronics\" rel=\"noopener noreferrer\">Awesome Open Electronics (⭐605)</a> - List with resources for Electronics Enthusiasts.</li>\n</ul>\n\n<ul>\n<li><a href=\"https://github.com/paulhendricks/awesome-open\" rel=\"noopener noreferrer\">Awesome Open (⭐85)</a> - A list of open companies and communities.</li>\n</ul>\n"
    }
  ]
}
